metrics.py
setup.py
statsdclient.py
pysvcmetrics.egg-info/PKG-INFO
pysvcmetrics.egg-info/SOURCES.txt
pysvcmetrics.egg-info/dependency_links.txt
pysvcmetrics.egg-info/top_level.txt
pysvcmetrics.egg-info/zip-safe