Metadata-Version: 1.0
Name: pysvcmetrics
Version: 0.1
Summary: Utilities to send metrics to graphite via statsd
Home-page: https://github.com/langloisjp/pysvcmetrics
Author: Jean-Philippe Langlois
Author-email: jpl@jplanglois.com
License: MIT
Platform: UNKNOWN
